{
    "code": 1,
    "message": "success",
    "data": [
        {
            "stockCode": "007801",
            "areaCode": "cn",
            "exchange": "jj",
            "market": "a",
            "name": "大成中证红利指数证券投资基金",
            "shortName": "大成中证红利指数C"
        },
        {
            "name": "富国中证红利指数增强A",
            "areaCode": "cn",
            "market": "a",
            "stockCode": "008682",
            "shortName": "富国中证红利指数增强C",
            "exchange": "jj"
        },
        {
            "stockCode": "008736",
            "name": "南方高股息主题股票型证券投资基金A类",
            "areaCode": "cn",
            "market": "a",
            "exchange": "jj",
            "shortName": "南方高股息主题股票A"
        },
        {
            "name": "南方高股息主题股票型证券投资基金A类",
            "areaCode": "cn",
            "market": "a",
            "stockCode": "008737",
            "shortName": "南方高股息主题股票C",
            "exchange": "jj"
        },
        {
            "stockCode": "009051",
            "name": "易方达中证红利ETF联接A",
            "areaCode": "cn",
            "market": "a",
            "exchange": "jj",
            "shortName": "易方达中证红利ETF联接发起式A"
        },
        {
            "name": "易方达中证红利ETF联接A",
            "areaCode": "cn",
            "market": "a",
            "stockCode": "009052",
            "shortName": "易方达中证红利ETF联接发起式C",
            "exchange": "jj"
        },
        {
            "stockCode": "012643",
            "shortName": "招商中证红利ETF联接A",
            "areaCode": "cn",
            "market": "a",
            "exchange": "jj",
            "name": "招商中证红利ETF联接A"
        },
        {
            "name": "招商中证红利ETF联接A",
            "areaCode": "cn",
            "market": "a",
            "stockCode": "012644",
            "shortName": "招商中证红利ETF联接C",
            "exchange": "jj"
        },
        {
            "name": "万家中证红利交易型开放式指数证券投资基金联接基金A",
            "areaCode": "cn",
            "market": "a",
            "stockCode": "015558",
            "shortName": "万家中证红利ETF联接C",
            "exchange": "jj"
        },
        {
            "stockCode": "020195",
            "areaCode": "cn",
            "market": "a",
            "exchange": "jj",
            "shortName": "汇添富中证红利ETF发起式联接A",
            "name": "汇添富中证红利交易型开放式指数证券投资基金发起式联接基金A"
        },
        {
            "name": "汇添富中证红利交易型开放式指数证券投资基金发起式联接基金A",
            "areaCode": "cn",
            "market": "a",
            "stockCode": "020196",
            "shortName": "汇添富中证红利ETF发起式联接C",
            "exchange": "jj"
        },
        {
            "stockCode": "021099",
            "areaCode": "cn",
            "market": "a",
            "exchange": "jj",
            "shortName": "博时中证红利ETF发起式联接A",
            "name": "博时中证红利交易型开放式指数证券投资基金发起式联接基金A"
        },
        {
            "name": "博时中证红利交易型开放式指数证券投资基金发起式联接基金A",
            "areaCode": "cn",
            "market": "a",
            "stockCode": "021100",
            "shortName": "博时中证红利ETF发起式联接C",
            "exchange": "jj"
        },
        {
            "stockCode": "090010",
            "areaCode": "cn",
            "exchange": "jj",
            "market": "a",
            "name": "大成中证红利指数证券投资基金",
            "shortName": "大成中证红利指数A"
        },
        {
            "stockCode": "100032",
            "areaCode": "cn",
            "exchange": "jj",
            "market": "a",
            "name": "富国中证红利指数增强A",
            "shortName": "富国中证红利指数增强A/B"
        },
        {
            "stockCode": "515080",
            "areaCode": "cn",
            "market": "a",
            "exchange": "sh",
            "name": "招商中证红利交易型开放式指数证券投资基金",
            "shortName": "招商中证红利ETF"
        },
        {
            "stockCode": "515180",
            "areaCode": "cn",
            "market": "a",
            "exchange": "sh",
            "name": "易方达中证红利交易型开放式指数证券投资基金",
            "shortName": "易方达中证红利ETF"
        },
        {
            "stockCode": "515890",
            "name": "博时中证红利交易型开放式指数证券投资基金",
            "areaCode": "cn",
            "market": "a",
            "exchange": "sh",
            "shortName": "博时中证红利ETF"
        },
        {
            "stockCode": "560020",
            "shortName": "汇添富中证红利ETF",
            "areaCode": "cn",
            "market": "a",
            "exchange": "sh",
            "name": "汇添富中证红利交易型开放式指数证券投资基金"
        },
        {
            "stockCode": "159581",
            "areaCode": "cn",
            "market": "a",
            "exchange": "sz",
            "shortName": "万家中证红利ETF",
            "name": "万家中证红利交易型开放式指数证券投资基金"
        },
        {
            "stockCode": "159589",
            "areaCode": "cn",
            "market": "a",
            "exchange": "sz",
            "shortName": "广发中证红利ETF",
            "name": "广发中证红利交易型开放式指数证券投资基金"
        },
        {
            "stockCode": "161907",
            "areaCode": "cn",
            "exchange": "sz",
            "market": "a",
            "name": "万家中证红利交易型开放式指数证券投资基金联接基金A",
            "shortName": "万家红利A"
        }
    ]
}