{
    "code": 1,
    "message": "success",
    "data": [
        {
            "stockCode": "007464",
            "areaCode": "cn",
            "market": "a",
            "exchange": "jj",
            "name": "交银施罗德创业板50指数型证券投资基金A",
            "shortName": "交银创业板50指数A"
        },
        {
            "stockCode": "007465",
            "areaCode": "cn",
            "market": "a",
            "exchange": "jj",
            "name": "交银施罗德创业板50指数型证券投资基金A",
            "shortName": "交银创业板50指数C"
        },
        {
            "name": "华安创业板50指数型证券投资基金",
            "areaCode": "cn",
            "market": "a",
            "stockCode": "014985",
            "shortName": "华安创业板50指数C",
            "exchange": "jj"
        },
        {
            "stockCode": "017949",
            "shortName": "景顺长城创业板50ETF联接A",
            "areaCode": "cn",
            "market": "a",
            "exchange": "jj",
            "name": "景顺长城创业板50交易型开放式指数证券投资基金联接基金A"
        },
        {
            "name": "景顺长城创业板50交易型开放式指数证券投资基金联接基金A",
            "areaCode": "cn",
            "market": "a",
            "stockCode": "017950",
            "shortName": "景顺长城创业板50ETF联接C",
            "exchange": "jj"
        },
        {
            "stockCode": "018482",
            "shortName": "鹏华创业板50ETF联接A",
            "areaCode": "cn",
            "market": "a",
            "exchange": "jj",
            "name": "鹏华创业板50交易型开放式指数证券投资基金联接基金A"
        },
        {
            "name": "鹏华创业板50交易型开放式指数证券投资基金联接基金A",
            "areaCode": "cn",
            "market": "a",
            "stockCode": "018483",
            "shortName": "鹏华创业板50ETF联接C",
            "exchange": "jj"
        },
        {
            "stockCode": "160420",
            "areaCode": "cn",
            "exchange": "jj",
            "market": "a",
            "name": "华安创业板50指数型证券投资基金",
            "shortName": "华安创业板50指数A"
        },
        {
            "stockCode": "160422",
            "areaCode": "cn",
            "exchange": "jj",
            "market": "a",
            "name": "华安创业板50交易型开放式指数证券投资基金联接基金A",
            "shortName": "华安创业板50ETF联接A"
        },
        {
            "stockCode": "160424",
            "areaCode": "cn",
            "exchange": "jj",
            "market": "a",
            "name": "华安创业板50交易型开放式指数证券投资基金联接基金A",
            "shortName": "华安创业板50ETF联接C"
        },
        {
            "stockCode": "159681",
            "shortName": "创50ETF",
            "areaCode": "cn",
            "market": "a",
            "exchange": "sz",
            "name": "鹏华创业板50交易型开放式指数证券投资基金"
        },
        {
            "stockCode": "159682",
            "shortName": "景顺长城创业板50ETF",
            "areaCode": "cn",
            "market": "a",
            "exchange": "sz",
            "name": "景顺长城创业板50交易型开放式指数证券投资基金"
        },
        {
            "stockCode": "159949",
            "areaCode": "cn",
            "exchange": "sz",
            "market": "a",
            "name": "华安创业板50交易型开放式指数证券投资基金",
            "shortName": "华安创业板50ETF"
        }
    ]
}