{
    "code": 1,
    "message": "success",
    "data": [
        {
            "areaCode": "cn",
            "stockCode": "008326",
            "exchange": "jj",
            "name": "西藏东财中证通信技术主题指数型发起式证券投资基金A类",
            "shortName": "东财通信A",
            "market": "a"
        },
        {
            "areaCode": "cn",
            "stockCode": "008327",
            "exchange": "jj",
            "name": "西藏东财中证通信技术主题指数型发起式证券投资基金A类",
            "shortName": "东财通信C",
            "market": "a"
        }
    ]
}